email_phone_user/models.py
email_phone_user/__init__.py
django_email_phone_user-1.0.3.dist-info/metadata.json
django_email_phone_user-1.0.3.dist-info/DESCRIPTION.rst
django_email_phone_user-1.0.3.dist-info/RECORD
django_email_phone_user-1.0.3.dist-info/WHEEL
django_email_phone_user-1.0.3.dist-info/top_level.txt
django_email_phone_user-1.0.3.dist-info/METADATA
