Metadata-Version: 2.0
Name: django-email-phone-user
Version: 1.0.3
Summary: Django Custom User model with email or phone as username
Home-page: https://github.com/168estate/django-email-phone-user
Author: 168 Estate Limited
Author-email: info@168.estate
License: MIT
Platform: UNKNOWN
Classifier: Development Status :: 5 - Production/Stable
Classifier: Environment :: Console
Classifier: License :: OSI Approved :: MIT License
Classifier: Natural Language :: English
Classifier: Operating System :: OS Independent
Classifier: Programming Language :: Python :: 2.7
Classifier: Programming Language :: Python :: 3.3
Classifier: Topic :: Software Development :: Libraries :: Python Modules
